errers/__init__.py
errers/_app.py
errers/_cli.py
errers/_gui.py
errers/_name.py
errers/_version.py
errers/_engine/__init__.py
errers/_engine/base.py
errers/_engine/extractor.py
errers/_engine/latex.py
errers/_engine/plain.py
errers/icon/errers.icns
errers/icon/errers.ico
errers/icon/errers.png
errers/icon/errers32.png
errers/rules/__init__.py
errers/rules/standard.py
errers-3.2.1.dist-info/LICENSES.txt
errers-3.2.1.dist-info/METADATA
errers-3.2.1.dist-info/WHEEL
errers-3.2.1.dist-info/entry_points.txt
errers-3.2.1.dist-info/top_level.txt
errers-3.2.1.dist-info/RECORD
