Metadata-Version: 2.1
Name: errers
Version: 3.2.1
Summary: ERRERS: Enhanced Review of Reports via Extraction using Rule-based Substitutions
Author-email: "Steve Guillouzic, Defence Research and Development Canada" <steve.guillouzic@forces.gc.ca>
Project-URL: User manual, https://cradpdf.drdc-rddc.gc.ca/PDFS/unc459/p813656_A1b.pdf
Project-URL: Change log, https://github.com/steve-guillouzic-gc/errers/blob/main/CHANGELOG.rst
Project-URL: Bug tracker, https://github.com/steve-guillouzic-gc/errers/issues
Project-URL: Source code, https://github.com/steve-guillouzic-gc/errers
Project-URL: Contribution guidelines, https://github.com/steve-guillouzic-gc/errers/blob/main/CONTRIBUTING.rst
Keywords: LaTeX,grammar,spelling,regular expression
Classifier: Development Status :: 5 - Production/Stable
Classifier: Environment :: Console
Classifier: Environment :: MacOS X
Classifier: Environment :: Win32 (MS Windows)
Classifier: Environment :: X11 Applications
Classifier: Intended Audience :: Science/Research
Classifier: License :: OSI Approved :: MIT License
Classifier: Natural Language :: English
Classifier: Operating System :: OS Independent
Classifier: Programming Language :: Python :: 3
Classifier: Programming Language :: Python :: 3.6
Classifier: Programming Language :: Python :: 3.7
Classifier: Programming Language :: Python :: 3.8
Classifier: Programming Language :: Python :: 3.9
Classifier: Programming Language :: Python :: 3.10
Classifier: Programming Language :: Python :: 3.11
Classifier: Programming Language :: Python :: 3.12
Classifier: Programming Language :: Python :: 3 :: Only
Classifier: Programming Language :: Python :: Implementation :: CPython
Classifier: Topic :: Text Processing :: Filters
Classifier: Topic :: Text Processing :: Markup :: LaTeX
Requires-Python: >=3.6
License-File: LICENSES.txt
Requires-Dist: regex
Requires-Dist: pywin32 <=305 ; platform_system == "Windows" and python_version < "3.8"
Requires-Dist: pywin32 ; platform_system == "Windows" and python_version >= "3.8"
